funny_package/__init__.py
funny_package/command_line.py
funny_package/text.py
funny_package/tests/__init__.py
funny_package/tests/test_command_line.py
funny_package/tests/test_joke.py
funny_package-0.4.data/scripts/funniest-joke
funny_package-0.4.dist-info/LICENSE
funny_package-0.4.dist-info/METADATA
funny_package-0.4.dist-info/WHEEL
funny_package-0.4.dist-info/entry_points.txt
funny_package-0.4.dist-info/top_level.txt
funny_package-0.4.dist-info/RECORD
