Metadata-Version: 2.1
Name: funny-package
Version: 0.4
Summary: The funniest joke in the world
Home-page: http://github.com/pawarrchetan/funny_package
Author: pawarrchetan
Author-email: pawarrchetan@gmail.com
License: MIT
Keywords: funniest joke comedy flying circus
Platform: UNKNOWN
Classifier: Programming Language :: Python :: 3
Classifier: License :: OSI Approved :: MIT License
Classifier: Operating System :: OS Independent
Classifier: Topic :: Text Processing :: Linguistic
Requires-Python: >=3.6
Requires-Dist: markdown
Requires-Dist: nose
Requires-Dist: six
